LICENSE
MANIFEST.in
README.rst
description_fixer.py
setup.py
nose_descriptionfixer.egg-info/PKG-INFO
nose_descriptionfixer.egg-info/SOURCES.txt
nose_descriptionfixer.egg-info/dependency_links.txt
nose_descriptionfixer.egg-info/entry_points.txt
nose_descriptionfixer.egg-info/not-zip-safe
nose_descriptionfixer.egg-info/top_level.txt