Metadata-Version: 1.0
Name: nose-descriptionfixer
Version: 0.0.4
Summary: A Nose plugin to fix the way tests are described when the verbose flag (-v) is used
Home-page: UNKNOWN
Author: Simon Weber
Author-email: simon@simonmweber.com
License: UNKNOWN
Platform: UNKNOWN
